{"polygons":[{"points":[{"x":2560.0,"y":725.0},{"x":2585.0,"y":925.0},{"x":2357.0,"y":1000.0}]},{"points":[{"x":2585.0,"y":925.0},{"x":2447.0,"y":1365.0},{"x":2357.0,"y":1000.0}]},{"points":[{"x":2357.0,"y":1000.0},{"x":2447.0,"y":1365.0},{"x":2216.0,"y":1375.0}]},{"points":[{"x":2155.0,"y":7.0},{"x":2198.0,"y":334.0},{"x":1748.0,"y":79.0}]},{"points":[{"x":2198.0,"y":334.0},{"x":2538.0,"y":221.0},{"x":2262.0,"y":534.0}]},{"points":[{"x":2538.0,"y":221.0},{"x":2560.0,"y":725.0},{"x":2262.0,"y":534.0}]},{"points":[{"x":2184.0,"y":830.0},{"x":2357.0,"y":1000.0},{"x":1848.0,"y":1013.0}]},{"points":[{"x":2198.0,"y":334.0},{"x":2262.0,"y":534.0},{"x":2043.0,"y":564.0}]},{"points":[{"x":2262.0,"y":534.0},{"x":2184.0,"y":830.0},{"x":2043.0,"y":564.0}]},{"points":[{"x":2184.0,"y":830.0},{"x":1848.0,"y":1013.0},{"x":2043.0,"y":564.0}]},{"points":[{"x":2216.0,"y":1375.0},{"x":2447.0,"y":1365.0},{"x":2319.0,"y":1823.0}]},{"points":[{"x":2087.0,"y":1768.0},{"x":2216.0,"y":1375.0},{"x":2319.0,"y":1823.0}]},{"points":[{"x":2087.0,"y":1768.0},{"x":1818.0,"y":1965.0},{"x":1669.0,"y":1746.0}]},{"points":[{"x":1669.0,"y":1746.0},{"x":1626.0,"y":1462.0},{"x":1877.0,"y":1395.0}]},{"points":[{"x":2087.0,"y":1768.0},{"x":2319.0,"y":1823.0},{"x":2209.0,"y":2076.0}]},{"points":[{"x":1818.0,"y":1965.0},{"x":2087.0,"y":1768.0},{"x":2209.0,"y":2076.0}]},{"points":[{"x":1669.0,"y":1746.0},{"x":1818.0,"y":1965.0},{"x":1310.0,"y":1853.0}]},{"points":[{"x":1626.0,"y":1462.0},{"x":1669.0,"y":1746.0},{"x":1310.0,"y":1853.0}]},{"points":[{"x":1493.0,"y":1003.0},{"x":1626.0,"y":1462.0},{"x":1210.0,"y":1263.0}]},{"points":[{"x":1626.0,"y":1462.0},{"x":1310.0,"y":1853.0},{"x":1210.0,"y":1263.0}]},{"points":[{"x":1748.0,"y":79.0},{"x":1646.0,"y":453.0},{"x":1185.0,"y":488.0}]},{"points":[{"x":1646.0,"y":453.0},{"x":1493.0,"y":1003.0},{"x":1185.0,"y":488.0}]},{"points":[{"x":1493.0,"y":1003.0},{"x":1210.0,"y":1263.0},{"x":1185.0,"y":488.0}]},{"points":[{"x":2155.0,"y":7.0},{"x":2538.0,"y":221.0},{"x":2198.0,"y":334.0},{"x":2537.0,"y":2.0}]},{"points":[{"x":2184.0,"y":830.0},{"x":2560.0,"y":725.0},{"x":2357.0,"y":1000.0},{"x":2262.0,"y":534.0}]},{"points":[{"x":2357.0,"y":1000.0},{"x":2216.0,"y":1375.0},{"x":1848.0,"y":1013.0},{"x":1877.0,"y":1395.0}]},{"points":[{"x":1748.0,"y":79.0},{"x":2198.0,"y":334.0},{"x":2043.0,"y":564.0},{"x":1646.0,"y":453.0}]},{"points":[{"x":1493.0,"y":1003.0},{"x":1848.0,"y":1013.0},{"x":1626.0,"y":1462.0},{"x":1877.0,"y":1395.0}]},{"points":[{"x":2216.0,"y":1375.0},{"x":2087.0,"y":1768.0},{"x":1877.0,"y":1395.0},{"x":1669.0,"y":1746.0}]},{"points":[{"x":2043.0,"y":564.0},{"x":1848.0,"y":1013.0},{"x":1646.0,"y":453.0},{"x":1493.0,"y":1003.0}]}]}