{"polygons":[{"points":[{"x":2026.0,"y":2288.0},{"x":2232.0,"y":2238.0},{"x":2225.0,"y":2536.0}]},{"points":[{"x":1769.0,"y":2461.0},{"x":2026.0,"y":2288.0},{"x":2225.0,"y":2536.0}]},{"points":[{"x":2281.0,"y":1902.0},{"x":1941.0,"y":1887.0},{"x":2143.0,"y":1676.0}]},{"points":[{"x":1941.0,"y":1887.0},{"x":2026.0,"y":2288.0},{"x":1807.0,"y":2112.0}]},{"points":[{"x":2026.0,"y":2288.0},{"x":1769.0,"y":2461.0},{"x":1807.0,"y":2112.0}]},{"points":[{"x":2081.0,"y":1378.0},{"x":2143.0,"y":1676.0},{"x":1893.0,"y":1453.0}]},{"points":[{"x":2081.0,"y":1378.0},{"x":2095.0,"y":1070.0},{"x":2308.0,"y":1018.0}]},{"points":[{"x":2225.0,"y":2536.0},{"x":2232.0,"y":2238.0},{"x":2587.0,"y":2416.0}]},{"points":[{"x":2095.0,"y":1070.0},{"x":2081.0,"y":1378.0},{"x":1909.0,"y":1245.0}]},{"points":[{"x":2081.0,"y":1378.0},{"x":1893.0,"y":1453.0},{"x":1909.0,"y":1245.0}]},{"points":[{"x":2308.0,"y":1018.0},{"x":2095.0,"y":1070.0},{"x":2273.0,"y":738.0}]},{"points":[{"x":1807.0,"y":2112.0},{"x":1769.0,"y":2461.0},{"x":1454.0,"y":1916.0}]},{"points":[{"x":1893.0,"y":1453.0},{"x":1759.0,"y":1682.0},{"x":1579.0,"y":1286.0}]},{"points":[{"x":1909.0,"y":1245.0},{"x":1893.0,"y":1453.0},{"x":1579.0,"y":1286.0}]},{"points":[{"x":1759.0,"y":1682.0},{"x":1454.0,"y":1916.0},{"x":1579.0,"y":1286.0}]},{"points":[{"x":1759.0,"y":1682.0},{"x":1941.0,"y":1887.0},{"x":1708.0,"y":1894.0}]},{"points":[{"x":1941.0,"y":1887.0},{"x":1807.0,"y":2112.0},{"x":1708.0,"y":1894.0}]},{"points":[{"x":1807.0,"y":2112.0},{"x":1454.0,"y":1916.0},{"x":1708.0,"y":1894.0}]},{"points":[{"x":1454.0,"y":1916.0},{"x":1759.0,"y":1682.0},{"x":1708.0,"y":1894.0}]},{"points":[{"x":2095.0,"y":1070.0},{"x":1909.0,"y":1245.0},{"x":1693.0,"y":776.0}]},{"points":[{"x":1909.0,"y":1245.0},{"x":1579.0,"y":1286.0},{"x":1693.0,"y":776.0}]},{"points":[{"x":2273.0,"y":738.0},{"x":2095.0,"y":1070.0},{"x":1693.0,"y":776.0}]},{"points":[{"x":2281.0,"y":1902.0},{"x":2143.0,"y":1676.0},{"x":2430.0,"y":1715.0}]},{"points":[{"x":2143.0,"y":1676.0},{"x":2081.0,"y":1378.0},{"x":2430.0,"y":1715.0}]},{"points":[{"x":2081.0,"y":1378.0},{"x":2308.0,"y":1018.0},{"x":2430.0,"y":1715.0}]},{"points":[{"x":1579.0,"y":1286.0},{"x":1454.0,"y":1916.0},{"x":1168.0,"y":1078.0}]},{"points":[{"x":1693.0,"y":776.0},{"x":1579.0,"y":1286.0},{"x":1168.0,"y":1078.0}]},{"points":[{"x":1876.0,"y":203.0},{"x":1693.0,"y":776.0},{"x":1478.0,"y":508.0}]},{"points":[{"x":1693.0,"y":776.0},{"x":1168.0,"y":1078.0},{"x":1478.0,"y":508.0}]},{"points":[{"x":2232.0,"y":2238.0},{"x":2281.0,"y":1902.0},{"x":2481.0,"y":1988.0}]},{"points":[{"x":2587.0,"y":2416.0},{"x":2232.0,"y":2238.0},{"x":2481.0,"y":1988.0}]},{"points":[{"x":2281.0,"y":1902.0},{"x":2430.0,"y":1715.0},{"x":2481.0,"y":1988.0}]},{"points":[{"x":1941.0,"y":1887.0},{"x":2232.0,"y":2238.0},{"x":2026.0,"y":2288.0},{"x":2281.0,"y":1902.0}]},{"points":[{"x":1941.0,"y":1887.0},{"x":1759.0,"y":1682.0},{"x":2143.0,"y":1676.0},{"x":1893.0,"y":1453.0}]},{"points":[{"x":2265.0,"y":334.0},{"x":2273.0,"y":738.0},{"x":1876.0,"y":203.0},{"x":1693.0,"y":776.0}]}]}